Metadata-Version: 2.1
Name: test_package_Sinyukhina_A_M
Version: 0.0.1
Summary: My Package
Author: Anna
